{
  "userProfile": {
    "monthlyIncome": 3500.00,
    "allocatedIncomePercentage": 20,
    "allocatedIncomeAmount": 700.00
  },
  "debts": [
    {
      "id": "debt-123",
      "lenderName": "VehicleMotors Corp.",
      "type": "Car Loan",
      "originalDebt": 20000.00,
      "remainingDebt": 10000.00,
      "amountPaid": 10000.00,
      "percentageCompleted": 50.00,
      "interestRate": 4.0,
      "minimumPayment": 300.00,
      "paymentHistory": [
        { "date": "2025-01-10", "amount": 300.00 },
        { "date": "2025-02-10", "amount": 300.00 },
        { "date": "2025-03-10", "amount": 300.00 },
        { "date": "2025-04-10", "amount": 350.00 },
        { "date": "2025-05-10", "amount": 300.00 },
        { "date": "2025-06-10", "amount": 300.00 }
      ],
      "expectedPaymentDates": [
        "2025-07-10",
        "2025-08-10",
        "2025-09-10",
        "2025-10-10",
        "2025-11-10",
        "2025-12-10",
        "2026-01-10",
        "2026-02-10",
        "2026-03-10"
      ],
      "loanTermMonths": 60 
    },
    {
      "id": "debt-456",
      "lenderName": "University Loan Servicing",
      "type": "Student Loan",
      "originalDebt": 15000.00, 
      "remainingDebt": 12000.00,
      "amountPaid": 3000.00,
      "percentageCompleted": 20.00,
      "interestRate": 5.5,
      "minimumPayment": 120.00,
      "paymentHistory": [
        { "date": "2025-01-05", "amount": 120.00 },
        { "date": "2025-02-05", "amount": 120.00 },
        { "date": "2025-03-05", "amount": 120.00 },
        { "date": "2025-04-05", "amount": 120.00 },
        { "date": "2025-05-05", "amount": 120.00 },
        { "date": "2025-06-05", "amount": 120.00 }
      ],
      "expectedPaymentDates": [
        "2025-07-05",
        "2025-08-05",
        "2025-09-05",
        "2025-10-05"
      ],
      "loanTermMonths": 120 
    },
    {
      "id": "debt-789",
      "lenderName": "City Bank",
      "type": "Credit Card",
      "originalDebt": 4000.00, 
      "remainingDebt": 1500.00,
      "amountPaid": 2500.00,
      "percentageCompleted": 62.50,
      "interestRate": 20.00,
      "minimumPayment": 75.00,
      "paymentHistory": [
        { "date": "2025-04-20", "amount": 150.00 },
        { "date": "2025-05-20", "amount": 200.00 },
        { "date": "2025-06-12", "amount": 100.00 }
      ],
      "expectedPaymentDates": [
        "2025-06-25",
        "2025-07-25",
        "2025-08-25"
      ], 
      "creditLimit": 6000.00
    }
  ],
  "dashboardOverview": {
    "totalDebtLeft": 23500.00,
    "totalDebtPaid": 15500.00,
    "totalOriginalDebt": 39000.00,
    "overallProgressPercentage": 39.74,
    "nextOverallPaymentDate": "2025-06-25"
  }
}